[
    {
        "name": "Sun",
        "mass": 1.989e30,
        "pos": [0.0, 0.0],
        "vel": [0.0, 0.0],
        "radius": 12,
        "color": "#fdbb84"
    },
    {
        "name": "Earth",
        "mass": 5.972e24,
        "pos": [1.496e11, 0.0],
        "vel": [0.0, 29780.0],
        "radius": 6,
        "color": "#4a90e2"
    },
    {
        "name": "Mars",
        "mass": 6.417e23,
        "pos": [2.279e11, 0.0],
        "vel": [0.0, 24130.0],
        "radius": 4,
        "color": "#c1440e"
    },
    {
        "name": "Jupiter",
        "mass": 1.898e27,
        "pos": [7.785e11, 0.0],
        "vel": [0.0, 13070.0],
        "radius": 10,
        "color": "#d8b365"
    }
]